{
    "instaloader": {
        "node_type": "Post",
        "version": "4.2.8"
    },
    "node": {
        "__typename": "GraphImage",
        "accessibility_caption": "Image may contain: one or more people, sunglasses, beard and closeup",
        "comments_disabled": false,
        "dimensions": {
            "height": 1080,
            "width": 1080
        },
        "display_url": "https://instagram.ffra1-1.fna.fbcdn.net/vp/d1bf57a7a05a7b817ce005906680edcf/5DC7ED61/t51.2885-15/e35/66660086_131096988149463_3309861147772930942_n.jpg?_nc_ht=instagram.ffra1-1.fna.fbcdn.net",
        "edge_liked_by": {
            "count": 1
        },
        "edge_media_preview_like": {
            "count": 1
        },
        "edge_media_to_caption": {
            "edges": [
                {
                    "node": {
                        "text": "Do we brunch? Yes. Yes we brunch! #aviators #beard #style #goodhairday #losangeles #brunch #dapper #sunday #easylikesundaymorning"
                    }
                }
            ]
        },
        "edge_media_to_comment": {
            "count": 0
        },
        "id": "2108260300940516264",
        "is_video": false,
        "owner": {
            "id": "2690270514"
        },
        "shortcode": "B1CC5Lbnhuo",
        "taken_at_timestamp": 1565544234,
        "thumbnail_resources": [
            {
                "config_height": 150,
                "config_width": 150,
                "src": "https://instagram.ffra1-1.fna.fbcdn.net/vp/d7d89c726fb7dfdc517a72e5cdc5d05c/5DE4FB23/t51.2885-15/e35/s150x150/66660086_131096988149463_3309861147772930942_n.jpg?_nc_ht=instagram.ffra1-1.fna.fbcdn.net"
            },
            {
                "config_height": 240,
                "config_width": 240,
                "src": "https://instagram.ffra1-1.fna.fbcdn.net/vp/a1dd6ab57ef16ff9ae287c29b1ee5bdf/5DDD4269/t51.2885-15/e35/s240x240/66660086_131096988149463_3309861147772930942_n.jpg?_nc_ht=instagram.ffra1-1.fna.fbcdn.net"
            },
            {
                "config_height": 320,
                "config_width": 320,
                "src": "https://instagram.ffra1-1.fna.fbcdn.net/vp/432071a3b2301ac89414fcfe922888b9/5DE5E0D3/t51.2885-15/e35/s320x320/66660086_131096988149463_3309861147772930942_n.jpg?_nc_ht=instagram.ffra1-1.fna.fbcdn.net"
            },
            {
                "config_height": 480,
                "config_width": 480,
                "src": "https://instagram.ffra1-1.fna.fbcdn.net/vp/87dff8cf13ff7c0ef6cca8bd7be89f35/5DCA4289/t51.2885-15/e35/s480x480/66660086_131096988149463_3309861147772930942_n.jpg?_nc_ht=instagram.ffra1-1.fna.fbcdn.net"
            },
            {
                "config_height": 640,
                "config_width": 640,
                "src": "https://instagram.ffra1-1.fna.fbcdn.net/vp/a0e5788288ee1735ebd00cb078dc8101/5DD70284/t51.2885-15/sh0.08/e35/s640x640/66660086_131096988149463_3309861147772930942_n.jpg?_nc_ht=instagram.ffra1-1.fna.fbcdn.net"
            }
        ],
        "thumbnail_src": "https://instagram.ffra1-1.fna.fbcdn.net/vp/a0e5788288ee1735ebd00cb078dc8101/5DD70284/t51.2885-15/sh0.08/e35/s640x640/66660086_131096988149463_3309861147772930942_n.jpg?_nc_ht=instagram.ffra1-1.fna.fbcdn.net"
    }
}