{
    "instaloader": {
        "node_type": "Post",
        "version": "4.2.8"
    },
    "node": {
        "__typename": "GraphSidecar",
        "accessibility_caption": "Image may contain: one or more people",
        "comments_disabled": false,
        "dimensions": {
            "height": 1080,
            "width": 1080
        },
        "display_url": "https://instagram.ffra1-1.fna.fbcdn.net/vp/8ff10098bfeded3772e590b53bbf1df9/5DD05042/t51.2885-15/e35/67476440_1296476910508487_7683368058865482393_n.jpg?_nc_ht=instagram.ffra1-1.fna.fbcdn.net",
        "edge_liked_by": {
            "count": 0
        },
        "edge_media_preview_like": {
            "count": 0
        },
        "edge_media_to_caption": {
            "edges": [
                {
                    "node": {
                        "text": "\ud83e\udd81\ud83e\udd93\ud83d\udc12\ud83d\udc3a\ud83d\udc03\ud83e\udd92\ud83d\udc2a\ud83d\udc10 #polishgirl#polskadziewczyna#blondegirl l#blueeyes#selfieZos\u0142em#zoo#Gdansk#smile#sunday#greatday#greetings#camel#happy#animals#osio\u0142#ci\u0105gniesw\u00f3jdoswego#l4l"
                    }
                }
            ]
        },
        "edge_media_to_comment": {
            "count": 0
        },
        "id": "2108257924506135513",
        "is_video": false,
        "owner": {
            "id": "1417420251"
        },
        "shortcode": "B1CCWmNFyvZ",
        "taken_at_timestamp": 1565543951,
        "thumbnail_resources": [
            {
                "config_height": 150,
                "config_width": 150,
                "src": "https://instagram.ffra1-1.fna.fbcdn.net/vp/69a8e78a691826643be2f0c38877a15a/5DD5317D/t51.2885-15/e35/s150x150/67476440_1296476910508487_7683368058865482393_n.jpg?_nc_ht=instagram.ffra1-1.fna.fbcdn.net"
            },
            {
                "config_height": 240,
                "config_width": 240,
                "src": "https://instagram.ffra1-1.fna.fbcdn.net/vp/d5c948401b46ab7d2bac35ef4819cd0d/5DE21F7B/t51.2885-15/e35/s240x240/67476440_1296476910508487_7683368058865482393_n.jpg?_nc_ht=instagram.ffra1-1.fna.fbcdn.net"
            },
            {
                "config_height": 320,
                "config_width": 320,
                "src": "https://instagram.ffra1-1.fna.fbcdn.net/vp/7eeae7f5df3e37c546b54d59c4c3b8c8/5DCE2505/t51.2885-15/e35/s320x320/67476440_1296476910508487_7683368058865482393_n.jpg?_nc_ht=instagram.ffra1-1.fna.fbcdn.net"
            },
            {
                "config_height": 480,
                "config_width": 480,
                "src": "https://instagram.ffra1-1.fna.fbcdn.net/vp/dc66584f44830ea5a38e6bfbfcfc8d55/5DE17442/t51.2885-15/e35/s480x480/67476440_1296476910508487_7683368058865482393_n.jpg?_nc_ht=instagram.ffra1-1.fna.fbcdn.net"
            },
            {
                "config_height": 640,
                "config_width": 640,
                "src": "https://instagram.ffra1-1.fna.fbcdn.net/vp/ebf5563352d0e8ab419e08d32ae7ac73/5DE23EF8/t51.2885-15/sh0.08/e35/s640x640/67476440_1296476910508487_7683368058865482393_n.jpg?_nc_ht=instagram.ffra1-1.fna.fbcdn.net"
            }
        ],
        "thumbnail_src": "https://instagram.ffra1-1.fna.fbcdn.net/vp/ebf5563352d0e8ab419e08d32ae7ac73/5DE23EF8/t51.2885-15/sh0.08/e35/s640x640/67476440_1296476910508487_7683368058865482393_n.jpg?_nc_ht=instagram.ffra1-1.fna.fbcdn.net"
    }
}