{
    "instaloader": {
        "node_type": "Post",
        "version": "4.2.8"
    },
    "node": {
        "__typename": "GraphImage",
        "accessibility_caption": "No photo description available.",
        "comments_disabled": false,
        "dimensions": {
            "height": 1350,
            "width": 1080
        },
        "display_url": "https://instagram.ffra1-1.fna.fbcdn.net/vp/bd3fb38b9df6a3153bb402d111b615f7/5DC78363/t51.2885-15/e35/p1080x1080/66707421_2406565429562638_5467238481914648536_n.jpg?_nc_ht=instagram.ffra1-1.fna.fbcdn.net",
        "edge_liked_by": {
            "count": 0
        },
        "edge_media_preview_like": {
            "count": 0
        },
        "edge_media_to_caption": {
            "edges": [
                {
                    "node": {
                        "text": "Urlaub von Wochenende.\n\u270c\ud83c\udffc\nHallo du sch\u00f6ne Zuckermelone! \n#weekendmood #yummy #strandliebe #melone #takemetothelakes #berlin #brandenburg #itsamatch #summervibes #birkis #summerinthecity #sunday"
                    }
                }
            ]
        },
        "edge_media_to_comment": {
            "count": 0
        },
        "id": "2108253180446838071",
        "is_video": false,
        "owner": {
            "id": "600017269"
        },
        "shortcode": "B1CBRj9Hw03",
        "taken_at_timestamp": 1565543385,
        "thumbnail_resources": [
            {
                "config_height": 150,
                "config_width": 150,
                "src": "https://instagram.ffra1-1.fna.fbcdn.net/vp/677fb57b14b6cfa03bfdf1992f5c6959/5DD7B44F/t51.2885-15/e35/c0.180.1440.1440/s150x150/66707421_2406565429562638_5467238481914648536_n.jpg?_nc_ht=instagram.ffra1-1.fna.fbcdn.net"
            },
            {
                "config_height": 240,
                "config_width": 240,
                "src": "https://instagram.ffra1-1.fna.fbcdn.net/vp/6608ed6d9a5b19ce1455793a16595eb7/5DE0A049/t51.2885-15/e35/c0.180.1440.1440/s240x240/66707421_2406565429562638_5467238481914648536_n.jpg?_nc_ht=instagram.ffra1-1.fna.fbcdn.net"
            },
            {
                "config_height": 320,
                "config_width": 320,
                "src": "https://instagram.ffra1-1.fna.fbcdn.net/vp/70a594eaa991fc8a207cc399b6e0a1aa/5DEDA137/t51.2885-15/e35/c0.180.1440.1440/s320x320/66707421_2406565429562638_5467238481914648536_n.jpg?_nc_ht=instagram.ffra1-1.fna.fbcdn.net"
            },
            {
                "config_height": 480,
                "config_width": 480,
                "src": "https://instagram.ffra1-1.fna.fbcdn.net/vp/80189db4603c9902990808e4d2235c2c/5DDD9C70/t51.2885-15/e35/c0.180.1440.1440/s480x480/66707421_2406565429562638_5467238481914648536_n.jpg?_nc_ht=instagram.ffra1-1.fna.fbcdn.net"
            },
            {
                "config_height": 640,
                "config_width": 640,
                "src": "https://instagram.ffra1-1.fna.fbcdn.net/vp/78ed0133de5884cf13929f37e24782c9/5DDA87D8/t51.2885-15/sh0.08/e35/c0.180.1440.1440/s640x640/66707421_2406565429562638_5467238481914648536_n.jpg?_nc_ht=instagram.ffra1-1.fna.fbcdn.net"
            }
        ],
        "thumbnail_src": "https://instagram.ffra1-1.fna.fbcdn.net/vp/78ed0133de5884cf13929f37e24782c9/5DDA87D8/t51.2885-15/sh0.08/e35/c0.180.1440.1440/s640x640/66707421_2406565429562638_5467238481914648536_n.jpg?_nc_ht=instagram.ffra1-1.fna.fbcdn.net"
    }
}